djs/__init__.py
djs/cli/__init__.py
djs/cli/djs.py
djs/job_scheduler/__init__.py
djs/job_scheduler/api.py
djs/job_scheduler/domainsetup.py
djs/job_scheduler/filehandler.py
djs/job_scheduler/job.py
djs/job_scheduler/scheduler.py
djs/perturbation_engine/__init__.py
djs/perturbation_engine/from_yaml.py
djs/perturbation_engine/parameter_editor.py
djs/perturbation_engine/parameter_specific_helpers.py
djs-1.0.0.dist-info/LICENSE
djs-1.0.0.dist-info/METADATA
djs-1.0.0.dist-info/WHEEL
djs-1.0.0.dist-info/entry_points.txt
djs-1.0.0.dist-info/top_level.txt
djs-1.0.0.dist-info/RECORD
