Metadata-Version: 2.1
Name: djs
Version: 1.0.0
Summary: A framework for varying model parameters and automating concurrent usage of the Wrf-hydro/National Water Model using Docker
Home-page: https://github.com/aaraney/NWM-Dockerized-Job-Scheduler
Author: Austin Raney
Author-email: aaraney@crimson.ua.edu
License: MIT License
Keywords: docker nwm hydrology cuahsi noaa owp nwc
Platform: UNKNOWN
Requires-Python: >=3.5
